ubiq_security/__init__.py
ubiq_security/algorithm.py
ubiq_security/auth.py
ubiq_security/common.py
ubiq_security/configuration.py
ubiq_security/credentials.py
ubiq_security/decrypt.py
ubiq_security/encrypt.py
ubiq_security/events.py
ubiq_security/version.py
ubiq_security/structured/__init__.py
ubiq_security/structured/common.py
ubiq_security/structured/decrypt.py
ubiq_security/structured/encrypt.py
ubiq_security/structured/lib/__init__.py
ubiq_security/structured/lib/ff1.py
ubiq_security/structured/lib/ff1_test.py
ubiq_security/structured/lib/ffx.py
ubiq_security/structured/lib/ffx_test.py
ubiq_security-2.3.3.dist-info/licenses/LICENSE
ubiq_security-2.3.3.dist-info/METADATA
ubiq_security-2.3.3.dist-info/WHEEL
ubiq_security-2.3.3.dist-info/top_level.txt
ubiq_security-2.3.3.dist-info/RECORD
